{
  "hero": {
    "type": "video",
    "title": "Precision Manufacturing Solutions",
    "enabled": true,
    "subtitle": "Delivering High-Quality Precision Components for Automotive, Pneumatic, and Hydraulic Industries",
    "backgroundImage": "https://images.unsplash.com/photo-1581291518857-4e27b48ff24e",
    "backgroundVideo": "https://example.com/manufacturing-process-video"
  },
  "meta": {
    "title": "Precision Components Manufacturing | Momai Brass",
    "description": "Expert precision parts manufacturing using CNC technology for automotive, pneumatic, and hydraulic sectors with 30 years of industry experience."
  },
  "sections": {
    "cta": {
      "type": "cta",
      "title": "Ready to Transform Your Manufacturing Needs?",
      "enabled": true,
      "subtitle": "Get custom precision components tailored to your exact specifications",
      "primaryCTA": {
        "text": "Request Quote",
        "action": "/contact"
      },
      "secondaryCTA": {
        "text": "Call Experts",
        "action": "tel:+91-123-456-7890"
      }
    },
    "services": {
      "type": "services",
      "items": [
        {
          "id": "custom-manufacturing",
          "image": "https://images.unsplash.com/photo-1581291518857-4e27b48ff24e",
          "title": "Custom Manufacturing",
          "description": "We specialize in creating precision components tailored to your specific requirements using advanced CNC machining technology. Our custom manufacturing services ensure high-quality, precise parts for diverse industrial applications.",
          "capabilities": [
            "Precision CNC Machining",
            "Material Versatility",
            "Complex Geometries",
            "Quick Turnaround Times"
          ]
        },
        {
          "id": "mass-production",
          "image": "https://images.unsplash.com/photo-1581291518857-4e27b48ff24e",
          "title": "Mass Production Services",
          "description": "Leveraging our 40+ CNC machines, we deliver high-volume precision component manufacturing with consistent quality and efficiency. Our mass production capabilities meet the demanding requirements of automotive and industrial sectors.",
          "capabilities": [
            "High-Volume Manufacturing",
            "Consistent Quality",
            "Scalable Production",
            "Cost-Effective Solutions"
          ]
        },
        {
          "id": "surface-finishing",
          "image": "https://images.unsplash.com/photo-1581291518857-4e27b48ff24e",
          "title": "Surface Finishing",
          "description": "Our advanced surface finishing techniques enhance the performance and aesthetics of precision components. We provide comprehensive finishing services to meet the highest industry standards.",
          "capabilities": [
            "Deburring",
            "Polishing",
            "Coating",
            "Surface Treatment"
          ]
        }
      ],
      "title": "Our Manufacturing Services",
      "enabled": true,
      "subtitle": "Comprehensive Precision Manufacturing Solutions for Diverse Industries"
    },
    "capabilities": {
      "type": "capabilities",
      "items": [
        {
          "id": "production-capacity",
          "title": "Production Capabilities",
          "metrics": [
            {
              "label": "CNC Machines",
              "value": "40+ Machines"
            },
            {
              "label": "Operating Capacity",
              "value": "24/7 Production"
            },
            {
              "label": "Delivery Timeline",
              "value": "2-4 Weeks Standard"
            }
          ],
          "description": "Our extensive production infrastructure enables rapid, high-quality manufacturing of precision components across multiple material types."
        },
        {
          "id": "technical-expertise",
          "title": "Technical Expertise",
          "metrics": [
            {
              "label": "Manufacturing Technology",
              "value": "Advanced CNC Machining"
            },
            {
              "label": "Industry Experience",
              "value": "30+ Years"
            },
            {
              "label": "Custom Solutions",
              "value": "Tailored Manufacturing"
            }
          ],
          "description": "With three decades of experience, we provide cutting-edge technical solutions for complex precision component manufacturing."
        },
        {
          "id": "quality-standards",
          "title": "Quality Assurance",
          "metrics": [
            {
              "label": "Precision Tolerance",
              "value": "±0.01mm"
            },
            {
              "label": "Quality Certification",
              "value": "ISO 9001:2015"
            },
            {
              "label": "Environmental Standard",
              "value": "ISO 14001:2015"
            }
          ],
          "description": "We maintain rigorous quality standards through advanced measurement techniques and internationally recognized certifications."
        }
      ],
      "title": "Our Manufacturing Capabilities",
      "enabled": true,
      "subtitle": "Advanced Technology and Precision Engineering"
    },
    "manufacturing-process": {
      "type": "manufacturing-process",
      "steps": [
        {
          "step": 1,
          "title": "Initial Consultation",
          "description": "Understand client requirements and technical specifications for precision components."
        },
        {
          "step": 2,
          "title": "Design & Engineering",
          "description": "Develop detailed manufacturing blueprints and process optimization strategies."
        },
        {
          "step": 3,
          "title": "CNC Machining",
          "description": "Precision manufacturing using state-of-the-art CNC machines across multiple material types."
        },
        {
          "step": 4,
          "title": "Quality Inspection",
          "description": "Comprehensive quality checks ensuring dimensional accuracy and performance standards."
        },
        {
          "step": 5,
          "title": "Surface Finishing",
          "description": "Apply advanced surface treatments and finishing techniques for enhanced component performance."
        },
        {
          "step": 6,
          "title": "Delivery & Support",
          "description": "Timely delivery with ongoing technical support and consultation."
        }
      ],
      "title": "Our Manufacturing Process",
      "enabled": true,
      "subtitle": "Systematic Approach to Precision Component Manufacturing"
    }
  }
}